tdbot/__init__.py
tdbot/api_client.py
tdbot/configuration.py
tdbot/rest.py
tdbot/api/__init__.py
tdbot/api/mouse_api.py
tdbot/api/static_api.py
tdbot/models/__init__.py
tdbot/models/element.py
tdbot/models/object.py
tdbot/models/target.py
test/__init__.py
test/test_element.py
test/test_mouse_api.py
test/test_object.py
test/test_static_api.py
test/test_target.py
tdbot-1.0.0.dist-info/LICENSE
tdbot-1.0.0.dist-info/METADATA
tdbot-1.0.0.dist-info/WHEEL
tdbot-1.0.0.dist-info/top_level.txt
tdbot-1.0.0.dist-info/RECORD
