Metadata-Version: 2.1
Name: tdbot
Version: 1.0.0
Summary: tdbot
Home-page: https://github.com/tdRPA/tdRPA
Author: Armstrong Wang
Author-email: Armstrong Wang <armstrong.wang@gmail.com>
Project-URL: Homepage, https://github.com/tdRPA/tdRPA
Project-URL: Bug Tracker, https://github.com/tdRPA/tdRPA/issues
Keywords: Swagger,tdBot - OpenAPI 3.0
Classifier: Programming Language :: Python :: 3
Classifier: License :: OSI Approved :: MIT License
Classifier: Operating System :: OS Independent
Requires-Python: >=3.8
License-File: LICENSE
Requires-Dist: urllib3 (>=1.15)
Requires-Dist: six (>=1.10)
Requires-Dist: certifi
Requires-Dist: python-dateutil
